{
  "category": ["Sport", "Team", "Player", "Tournament"],
  "sport": ["NFL", "NBA", "MLB", "NHL", "Tennis", "Golf", "Boxing", "UFC"],
  "NFL": [
    "Oakland Raiders",
    "San Francisco 49ers",
    "Denver Broncos",
    "Seattle Seahawks"
  ],
  "Raiders": [
    "Terrelle Pryor",
    "Darren McFadden",
    "Denarius Moore",
    "Rod Streater",
    "Charles Woodson"
  ],
  "49ers": [
    "Colin Kaepernick",
    "Frank Gore",
    "Anquan Boldin",
    "Navorro Bowman",
    "Aldon Smith"
  ],
  "NBA": [
    "Miami Heat",
    "Golden State Warriors",
    "San Antonio Spurs",
    "Indiana Pacers"
  ],
  "Warriors": [
    "David Lee",
    "Stephen Curry",
    "Andre Iguodala"
  ],
  "Heat": [
    "Lebron James",
    "Dwyane Wade",
    "Chris Bosh"
  ]
}
